libumccr/__init__.py
libumccr/libdt.py
libumccr/libgdrive.py
libumccr/libjson.py
libumccr/libregex.py
libumccr/libslack.py
libumccr/utils.py
libumccr/aws/__init__.py
libumccr/aws/libeb.py
libumccr/aws/liblambda.py
libumccr/aws/libs3.py
libumccr/aws/libsm.py
libumccr/aws/libsqs.py
libumccr/aws/libssm.py
libumccr-0.4.1.dist-info/LICENSE
libumccr-0.4.1.dist-info/METADATA
libumccr-0.4.1.dist-info/WHEEL
libumccr-0.4.1.dist-info/top_level.txt
libumccr-0.4.1.dist-info/RECORD
