Metadata-Version: 2.1
Name: libumccr
Version: 0.4.1
Summary: UMCCR Reusable Python modules
Home-page: https://github.com/umccr/libumccr
Author: UMCCR and Contributors
Author-email: services@umccr.org
License: MIT
Project-URL: Bug Tracker, https://github.com/umccr/libumccr/issues
Classifier: Development Status :: 5 - Production/Stable
Classifier: Programming Language :: Python :: 3
Classifier: License :: OSI Approved :: MIT License
Classifier: Operating System :: OS Independent
Requires-Python: >=3.9
License-File: LICENSE
Provides-Extra: all
Requires-Dist: Django; extra == "all"
Requires-Dist: boto3; extra == "all"
Requires-Dist: botocore; extra == "all"
Requires-Dist: cachetools; extra == "all"
Requires-Dist: requests; extra == "all"
Requires-Dist: pandas; extra == "all"
Requires-Dist: gspread; extra == "all"
Requires-Dist: gspread-pandas; extra == "all"
Requires-Dist: google-auth; extra == "all"
Provides-Extra: aws
Requires-Dist: boto3; extra == "aws"
Requires-Dist: botocore; extra == "aws"
Requires-Dist: cachetools; extra == "aws"
Provides-Extra: dev
Requires-Dist: pipdeptree; extra == "dev"
Requires-Dist: twine; extra == "dev"
Requires-Dist: setuptools; extra == "dev"
Requires-Dist: wheel; extra == "dev"
Requires-Dist: build; extra == "dev"
Requires-Dist: pdoc3; extra == "dev"
Requires-Dist: pre-commit; extra == "dev"
Requires-Dist: detect-secrets; extra == "dev"
Provides-Extra: libgdrive
Requires-Dist: requests; extra == "libgdrive"
Requires-Dist: pandas; extra == "libgdrive"
Requires-Dist: gspread; extra == "libgdrive"
Requires-Dist: gspread-pandas; extra == "libgdrive"
Requires-Dist: google-auth; extra == "libgdrive"
Requires-Dist: cachetools; extra == "libgdrive"
Provides-Extra: test
Requires-Dist: pytest; extra == "test"
Requires-Dist: pytest-cov; extra == "test"
Requires-Dist: flake8; extra == "test"
Requires-Dist: mockito; extra == "test"
Requires-Dist: tox; extra == "test"
Requires-Dist: nose2; extra == "test"
Requires-Dist: awscli-local; extra == "test"
Requires-Dist: cachetools; extra == "test"
